netgsm/__init__.py
netgsm/netgsm.py
netgsm/exceptions/__init__.py
netgsm/exceptions/api_exception.py
netgsm/sms/__init__.py
netgsm/sms/sms_service.py
netgsm/utils/__init__.py
netgsm/utils/config.py
netgsm/utils/enums.py
netgsm_sms-1.1.2.dist-info/LICENSE
netgsm_sms-1.1.2.dist-info/METADATA
netgsm_sms-1.1.2.dist-info/WHEEL
netgsm_sms-1.1.2.dist-info/top_level.txt
netgsm_sms-1.1.2.dist-info/RECORD
